graphsciics/__init__.py
graphsciics/animate.py
graphsciics/custom.py
graphsciics/graphsciics.py
graphsciics-0.0.3.dist-info/LICENSE
graphsciics-0.0.3.dist-info/METADATA
graphsciics-0.0.3.dist-info/WHEEL
graphsciics-0.0.3.dist-info/top_level.txt
graphsciics-0.0.3.dist-info/RECORD
